slackdown/__init__.py
slackdown/templates.py
slackdown/tests.py
slackdown-0.0.3.dist-info/DESCRIPTION.rst
slackdown-0.0.3.dist-info/LICENSE.txt
slackdown-0.0.3.dist-info/METADATA
slackdown-0.0.3.dist-info/RECORD
slackdown-0.0.3.dist-info/WHEEL
slackdown-0.0.3.dist-info/metadata.json
slackdown-0.0.3.dist-info/top_level.txt
